package_name/__init__.py
package_name/module1_name/__init__.py
package_name/module1_name/file1_name.py
package_name/module1_name/file2_name.py
package_name/module2_name/__init__.py
package_name/module2_name/file1_name.py
package_name/module2_name/file2_name.py
package_dio-0.0.1.dist-info/METADATA
package_dio-0.0.1.dist-info/WHEEL
package_dio-0.0.1.dist-info/top_level.txt
package_dio-0.0.1.dist-info/RECORD
