Metadata-Version: 2.4
Name: package_dio
Version: 0.0.1
Summary: Tech student
Home-page: https://github.com/heitorpcrl/Python-package-DIO.git
Author: Heitor
Author-email: heitorphantom@gmail.com
Requires-Python: >=3.8
Dynamic: author
Dynamic: author-email
Dynamic: description
Dynamic: description-content-type
Dynamic: home-page
Dynamic: requires-python
Dynamic: summary
